[{"gazeX":756.8295,"gazeY":172.844879,"timestamp":170585072.0,"idLine":0,"duration":192.0,"squaredVelocity":0.0,"isReading":false,"idFixation":1},{"gazeX":850.4103,"gazeY":171.16803,"timestamp":170585312.0,"idLine":0,"duration":160.0,"squaredVelocity":0.0,"isReading":false,"idFixation":2},{"gazeX":1800.72717,"gazeY":344.886841,"timestamp":170585728.0,"idLine":0,"duration":352.0,"squaredVelocity":0.0,"isReading":false,"idFixation":3},{"gazeX":1805.348,"gazeY":354.029083,"timestamp":170586080.0,"idLine":0,"duration":512.0,"squaredVelocity":0.0,"isReading":false,"idFixation":4},{"gazeX":1453.79968,"gazeY":816.2551,"timestamp":170586736.0,"idLine":0,"duration":176.0,"squaredVelocity":0.0,"isReading":false,"idFixation":5},{"gazeX":1252.67761,"gazeY":890.4439,"timestamp":170586976.0,"idLine":0,"duration":144.0,"squaredVelocity":0.0,"isReading":false,"idFixation":6},{"gazeX":1635.09656,"gazeY":988.7859,"timestamp":170587232.0,"idLine":0,"duration":112.0,"squaredVelocity":0.0,"isReading":false,"idFixation":7},{"gazeX":565.7929,"gazeY":1815.5625,"timestamp":170587680.0,"idLine":0,"duration":288.0,"squaredVelocity":0.0,"isReading":false,"idFixation":8},{"gazeX":595.199646,"gazeY":244.466278,"timestamp":170589072.0,"idLine":0,"duration":272.0,"squaredVelocity":0.0,"isReading":false,"idFixation":9},{"gazeX":877.215942,"gazeY":686.2812,"timestamp":170589440.0,"idLine":0,"duration":256.0,"squaredVelocity":0.0,"isReading":false,"idFixation":10},{"gazeX":671.1553,"gazeY":698.0096,"timestamp":170589776.0,"idLine":0,"duration":176.0,"squaredVelocity":0.0,"isReading":false,"idFixation":11},{"gazeX":618.030334,"gazeY":920.9675,"timestamp":170590016.0,"idLine":0,"duration":256.0,"squaredVelocity":0.0,"isReading":false,"idFixation":12},{"gazeX":649.1789,"gazeY":379.217438,"timestamp":1.705906E+08,"idLine":0,"duration":320.0,"squaredVelocity":0.0,"isReading":false,"idFixation":13},{"gazeX":726.002869,"gazeY":500.2048,"timestamp":1.70591E+08,"idLine":0,"duration":208.0,"squaredVelocity":0.0,"isReading":false,"idFixation":14},{"gazeX":745.916931,"gazeY":899.146545,"timestamp":170591328.0,"idLine":0,"duration":176.0,"squaredVelocity":0.0,"isReading":false,"idFixation":15},{"gazeX":894.0565,"gazeY":994.5702,"timestamp":170591616.0,"idLine":0,"duration":176.0,"squaredVelocity":0.0,"isReading":false,"idFixation":16},{"gazeX":1830.21008,"gazeY":994.717346,"timestamp":170592240.0,"idLine":0,"duration":224.0,"squaredVelocity":0.0,"isReading":false,"idFixation":17},{"gazeX":816.223633,"gazeY":343.136963,"timestamp":170592576.0,"idLine":0,"duration":208.0,"squaredVelocity":0.0,"isReading":false,"idFixation":18},{"gazeX":676.0191,"gazeY":385.181763,"timestamp":170592816.0,"idLine":0,"duration":256.0,"squaredVelocity":0.0,"isReading":false,"idFixation":19},{"gazeX":685.9585,"gazeY":409.5454,"timestamp":170593072.0,"idLine":0,"duration":224.0,"squaredVelocity":0.0,"isReading":false,"idFixation":20},{"gazeX":778.6093,"gazeY":405.740753,"timestamp":170593328.0,"idLine":0,"duration":256.0,"squaredVelocity":0.0,"isReading":false,"idFixation":21},{"gazeX":1712.99878,"gazeY":896.6433,"timestamp":170593744.0,"idLine":0,"duration":160.0,"squaredVelocity":0.0,"isReading":false,"idFixation":22},{"gazeX":1796.31665,"gazeY":966.8152,"timestamp":170593936.0,"idLine":0,"duration":160.0,"squaredVelocity":0.0,"isReading":false,"idFixation":23},{"gazeX":845.4458,"gazeY":1479.15649,"timestamp":170594336.0,"idLine":0,"duration":176.0,"squaredVelocity":0.0,"isReading":false,"idFixation":24},{"gazeX":1771.64526,"gazeY":1017.81451,"timestamp":170594624.0,"idLine":0,"duration":288.0,"squaredVelocity":0.0,"isReading":false,"idFixation":25},{"gazeX":1803.46777,"gazeY":980.311035,"timestamp":170594912.0,"idLine":0,"duration":176.0,"squaredVelocity":0.0,"isReading":false,"idFixation":26},{"gazeX":1003.3653,"gazeY":362.6735,"timestamp":1.705952E+08,"idLine":0,"duration":336.0,"squaredVelocity":0.0,"isReading":false,"idFixation":27},{"gazeX":1718.70154,"gazeY":290.158539,"timestamp":170595712.0,"idLine":0,"duration":128.0,"squaredVelocity":0.0,"isReading":false,"idFixation":28},{"gazeX":745.5557,"gazeY":852.2542,"timestamp":170606240.0,"idLine":0,"duration":272.0,"squaredVelocity":0.0,"isReading":false,"idFixation":29},{"gazeX":1701.5929,"gazeY":986.579346,"timestamp":170606848.0,"idLine":0,"duration":304.0,"squaredVelocity":0.0,"isReading":false,"idFixation":30},{"gazeX":1797.1665,"gazeY":981.474,"timestamp":170607264.0,"idLine":0,"duration":320.0,"squaredVelocity":0.0,"isReading":false,"idFixation":31},{"gazeX":1619.59436,"gazeY":358.744171,"timestamp":170611424.0,"idLine":0,"duration":128.0,"squaredVelocity":0.0,"isReading":false,"idFixation":32},{"gazeX":1143.52734,"gazeY":461.513367,"timestamp":170611664.0,"idLine":0,"duration":192.0,"squaredVelocity":0.0,"isReading":false,"idFixation":33},{"gazeX":1139.33582,"gazeY":470.6704,"timestamp":170611872.0,"idLine":0,"duration":192.0,"squaredVelocity":0.0,"isReading":false,"idFixation":34},{"gazeX":1791.51758,"gazeY":800.5966,"timestamp":170612128.0,"idLine":0,"duration":256.0,"squaredVelocity":0.0,"isReading":false,"idFixation":35},{"gazeX":1379.37012,"gazeY":660.2937,"timestamp":170612576.0,"idLine":0,"duration":256.0,"squaredVelocity":0.0,"isReading":false,"idFixation":36},{"gazeX":1116.34924,"gazeY":569.8758,"timestamp":170612912.0,"idLine":0,"duration":464.0,"squaredVelocity":0.0,"isReading":false,"idFixation":37},{"gazeX":1200.2688,"gazeY":585.62616,"timestamp":170613440.0,"idLine":0,"duration":288.0,"squaredVelocity":0.0,"isReading":false,"idFixation":38},{"gazeX":1419.56653,"gazeY":331.9051,"timestamp":170613808.0,"idLine":0,"duration":144.0,"squaredVelocity":0.0,"isReading":false,"idFixation":39},{"gazeX":1417.53723,"gazeY":315.140961,"timestamp":170613952.0,"idLine":0,"duration":400.0,"squaredVelocity":0.0,"isReading":false,"idFixation":40},{"gazeX":678.8072,"gazeY":171.653473,"timestamp":170617936.0,"idLine":0,"duration":352.0,"squaredVelocity":0.0,"isReading":false,"idFixation":41},{"gazeX":742.1374,"gazeY":1680.18713,"timestamp":170619632.0,"idLine":0,"duration":208.0,"squaredVelocity":0.0,"isReading":false,"idFixation":42},{"gazeX":564.2911,"gazeY":177.934647,"timestamp":170621360.0,"idLine":0,"duration":240.0,"squaredVelocity":0.0,"isReading":true,"idFixation":43},{"gazeX":707.4558,"gazeY":234.419083,"timestamp":170621840.0,"idLine":0,"duration":224.0,"squaredVelocity":0.0,"isReading":true,"idFixation":44},{"gazeX":761.753235,"gazeY":44.90398,"timestamp":170622272.0,"idLine":0,"duration":176.0,"squaredVelocity":0.0,"isReading":true,"idFixation":45},{"gazeX":853.788147,"gazeY":86.8271,"timestamp":170622480.0,"idLine":0,"duration":160.0,"squaredVelocity":0.0,"isReading":true,"idFixation":46},{"gazeX":924.998047,"gazeY":178.198883,"timestamp":170622768.0,"idLine":0,"duration":208.0,"squaredVelocity":0.0,"isReading":true,"idFixation":47},{"gazeX":975.3841,"gazeY":187.597244,"timestamp":170622992.0,"idLine":0,"duration":176.0,"squaredVelocity":0.0,"isReading":true,"idFixation":48},{"gazeX":1025.2085,"gazeY":189.286911,"timestamp":170623184.0,"idLine":0,"duration":160.0,"squaredVelocity":0.0,"isReading":true,"idFixation":49},{"gazeX":1115.40674,"gazeY":185.304138,"timestamp":170623360.0,"idLine":0,"duration":288.0,"squaredVelocity":0.0,"isReading":true,"idFixation":50},{"gazeX":1201.11743,"gazeY":183.528259,"timestamp":170623712.0,"idLine":0,"duration":160.0,"squaredVelocity":0.0,"isReading":true,"idFixation":51},{"gazeX":552.4823,"gazeY":204.761734,"timestamp":170624064.0,"idLine":0,"duration":160.0,"squaredVelocity":0.0,"isReading":true,"idFixation":52},{"gazeX":531.3545,"gazeY":205.204239,"timestamp":170624224.0,"idLine":0,"duration":400.0,"squaredVelocity":0.0,"isReading":true,"idFixation":53},{"gazeX":550.7759,"gazeY":246.158615,"timestamp":1.706248E+08,"idLine":0,"duration":464.0,"squaredVelocity":0.0,"isReading":true,"idFixation":54},{"gazeX":601.0782,"gazeY":251.534348,"timestamp":170625280.0,"idLine":0,"duration":272.0,"squaredVelocity":0.0,"isReading":true,"idFixation":55},{"gazeX":652.7371,"gazeY":255.516464,"timestamp":170625568.0,"idLine":0,"duration":224.0,"squaredVelocity":0.0,"isReading":true,"idFixation":56},{"gazeX":703.9936,"gazeY":254.4626,"timestamp":170625824.0,"idLine":0,"duration":176.0,"squaredVelocity":0.0,"isReading":true,"idFixation":57},{"gazeX":773.5748,"gazeY":247.334488,"timestamp":1.70626E+08,"idLine":0,"duration":272.0,"squaredVelocity":0.0,"isReading":true,"idFixation":58},{"gazeX":822.610046,"gazeY":246.267761,"timestamp":170626320.0,"idLine":0,"duration":160.0,"squaredVelocity":0.0,"isReading":true,"idFixation":59},{"gazeX":887.2594,"gazeY":247.829819,"timestamp":170626480.0,"idLine":0,"duration":272.0,"squaredVelocity":0.0,"isReading":true,"idFixation":60},{"gazeX":936.1561,"gazeY":250.370743,"timestamp":170626832.0,"idLine":0,"duration":384.0,"squaredVelocity":0.0,"isReading":true,"idFixation":61},{"gazeX":1004.33533,"gazeY":246.961639,"timestamp":170627232.0,"idLine":0,"duration":112.0,"squaredVelocity":0.0,"isReading":true,"idFixation":62},{"gazeX":1074.571,"gazeY":253.278748,"timestamp":170627424.0,"idLine":0,"duration":272.0,"squaredVelocity":0.0,"isReading":true,"idFixation":63},{"gazeX":1206.10022,"gazeY":247.395523,"timestamp":170627872.0,"idLine":0,"duration":288.0,"squaredVelocity":0.0,"isReading":true,"idFixation":64},{"gazeX":1261.4259,"gazeY":251.12233,"timestamp":170628176.0,"idLine":0,"duration":192.0,"squaredVelocity":0.0,"isReading":true,"idFixation":65},{"gazeX":1318.55042,"gazeY":249.718445,"timestamp":1.706284E+08,"idLine":0,"duration":512.0,"squaredVelocity":0.0,"isReading":true,"idFixation":66},{"gazeX":529.9433,"gazeY":271.679382,"timestamp":170629024.0,"idLine":0,"duration":400.0,"squaredVelocity":0.0,"isReading":true,"idFixation":67},{"gazeX":569.1222,"gazeY":281.748932,"timestamp":170629440.0,"idLine":0,"duration":512.0,"squaredVelocity":0.0,"isReading":true,"idFixation":68},{"gazeX":641.0637,"gazeY":290.231262,"timestamp":170630048.0,"idLine":0,"duration":256.0,"squaredVelocity":0.0,"isReading":true,"idFixation":69},{"gazeX":682.4982,"gazeY":286.561859,"timestamp":170630320.0,"idLine":0,"duration":144.0,"squaredVelocity":0.0,"isReading":true,"idFixation":70},{"gazeX":746.359131,"gazeY":281.154236,"timestamp":170630544.0,"idLine":0,"duration":224.0,"squaredVelocity":0.0,"isReading":true,"idFixation":71},{"gazeX":814.335754,"gazeY":274.6391,"timestamp":1.706308E+08,"idLine":0,"duration":192.0,"squaredVelocity":0.0,"isReading":true,"idFixation":72},{"gazeX":863.171448,"gazeY":276.654419,"timestamp":170631088.0,"idLine":0,"duration":288.0,"squaredVelocity":0.0,"isReading":true,"idFixation":73},{"gazeX":902.4672,"gazeY":275.365631,"timestamp":170631376.0,"idLine":0,"duration":144.0,"squaredVelocity":0.0,"isReading":true,"idFixation":74},{"gazeX":958.6908,"gazeY":273.032745,"timestamp":170631568.0,"idLine":0,"duration":272.0,"squaredVelocity":0.0,"isReading":true,"idFixation":75},{"gazeX":1057.85132,"gazeY":278.569733,"timestamp":170631872.0,"idLine":0,"duration":160.0,"squaredVelocity":0.0,"isReading":true,"idFixation":76},{"gazeX":1068.62512,"gazeY":280.133545,"timestamp":170632048.0,"idLine":0,"duration":240.0,"squaredVelocity":0.0,"isReading":true,"idFixation":77},{"gazeX":1119.66284,"gazeY":279.66098,"timestamp":1.706323E+08,"idLine":0,"duration":256.0,"squaredVelocity":0.0,"isReading":true,"idFixation":78},{"gazeX":1177.214,"gazeY":277.635559,"timestamp":170632640.0,"idLine":0,"duration":304.0,"squaredVelocity":0.0,"isReading":true,"idFixation":79},{"gazeX":1223.37048,"gazeY":280.53653,"timestamp":170632960.0,"idLine":0,"duration":112.0,"squaredVelocity":0.0,"isReading":true,"idFixation":80},{"gazeX":1240.87378,"gazeY":285.197479,"timestamp":170633088.0,"idLine":0,"duration":224.0,"squaredVelocity":0.0,"isReading":true,"idFixation":81},{"gazeX":1321.25732,"gazeY":280.6022,"timestamp":170633392.0,"idLine":0,"duration":208.0,"squaredVelocity":0.0,"isReading":true,"idFixation":82},{"gazeX":1342.96948,"gazeY":280.733276,"timestamp":170633616.0,"idLine":0,"duration":272.0,"squaredVelocity":0.0,"isReading":true,"idFixation":83},{"gazeX":1015.1601,"gazeY":609.4231,"timestamp":170685264.0,"idLine":0,"duration":320.0,"squaredVelocity":0.0,"isReading":false,"idFixation":256},{"gazeX":1793.4967,"gazeY":283.729767,"timestamp":170685776.0,"idLine":0,"duration":176.0,"squaredVelocity":0.0,"isReading":false,"idFixation":257},{"gazeX":1654.56812,"gazeY":263.044,"timestamp":170685952.0,"idLine":0,"duration":112.0,"squaredVelocity":0.0,"isReading":false,"idFixation":258},{"gazeX":1108.231,"gazeY":663.891541,"timestamp":170686160.0,"idLine":0,"duration":128.0,"squaredVelocity":0.0,"isReading":false,"idFixation":259},{"gazeX":929.0963,"gazeY":633.2794,"timestamp":170686384.0,"idLine":0,"duration":144.0,"squaredVelocity":0.0,"isReading":false,"idFixation":260},{"gazeX":1012.06952,"gazeY":160.956772,"timestamp":170687376.0,"idLine":0,"duration":112.0,"squaredVelocity":0.0,"isReading":false,"idFixation":261},{"gazeX":568.4206,"gazeY":202.562744,"timestamp":170687568.0,"idLine":0,"duration":192.0,"squaredVelocity":0.0,"isReading":false,"idFixation":262},{"gazeX":642.6368,"gazeY":1779.982,"timestamp":170687872.0,"idLine":0,"duration":256.0,"squaredVelocity":0.0,"isReading":false,"idFixation":263},{"gazeX":550.1108,"gazeY":241.741669,"timestamp":170688384.0,"idLine":0,"duration":176.0,"squaredVelocity":0.0,"isReading":false,"idFixation":264},{"gazeX":532.7926,"gazeY":191.530441,"timestamp":170688576.0,"idLine":0,"duration":320.0,"squaredVelocity":0.0,"isReading":false,"idFixation":265},{"gazeX":571.802856,"gazeY":189.601517,"timestamp":1.706889E+08,"idLine":0,"duration":224.0,"squaredVelocity":0.0,"isReading":false,"idFixation":266},{"gazeX":710.4472,"gazeY":536.3259,"timestamp":170730912.0,"idLine":0,"duration":256.0,"squaredVelocity":0.0,"isReading":false,"idFixation":409},{"gazeX":806.166565,"gazeY":520.654358,"timestamp":170731712.0,"idLine":0,"duration":112.0,"squaredVelocity":0.0,"isReading":false,"idFixation":410},{"gazeX":730.382751,"gazeY":517.170532,"timestamp":170731824.0,"idLine":0,"duration":144.0,"squaredVelocity":0.0,"isReading":false,"idFixation":411},{"gazeX":546.4073,"gazeY":562.2668,"timestamp":170732032.0,"idLine":0,"duration":176.0,"squaredVelocity":0.0,"isReading":false,"idFixation":412},{"gazeX":550.1796,"gazeY":361.1292,"timestamp":1.707324E+08,"idLine":0,"duration":224.0,"squaredVelocity":0.0,"isReading":false,"idFixation":413},{"gazeX":552.515442,"gazeY":326.080017,"timestamp":170732624.0,"idLine":0,"duration":112.0,"squaredVelocity":0.0,"isReading":false,"idFixation":414},{"gazeX":1480.24976,"gazeY":339.409973,"timestamp":170732944.0,"idLine":0,"duration":208.0,"squaredVelocity":0.0,"isReading":false,"idFixation":415},{"gazeX":760.1652,"gazeY":1741.59729,"timestamp":170733472.0,"idLine":0,"duration":160.0,"squaredVelocity":0.0,"isReading":false,"idFixation":416},{"gazeX":478.018555,"gazeY":197.286118,"timestamp":170733808.0,"idLine":0,"duration":144.0,"squaredVelocity":0.0,"isReading":true,"idFixation":417},{"gazeX":553.7917,"gazeY":174.0828,"timestamp":170733952.0,"idLine":0,"duration":224.0,"squaredVelocity":0.0,"isReading":true,"idFixation":418},{"gazeX":603.9116,"gazeY":191.097748,"timestamp":170734192.0,"idLine":0,"duration":112.0,"squaredVelocity":0.0,"isReading":true,"idFixation":419},{"gazeX":621.0422,"gazeY":196.179321,"timestamp":1.707343E+08,"idLine":0,"duration":512.0,"squaredVelocity":0.0,"isReading":true,"idFixation":420},{"gazeX":666.344055,"gazeY":179.576233,"timestamp":170734816.0,"idLine":0,"duration":272.0,"squaredVelocity":0.0,"isReading":true,"idFixation":421},{"gazeX":714.061157,"gazeY":192.305847,"timestamp":1.707351E+08,"idLine":0,"duration":224.0,"squaredVelocity":0.0,"isReading":true,"idFixation":422},{"gazeX":785.1419,"gazeY":201.653152,"timestamp":170735360.0,"idLine":0,"duration":192.0,"squaredVelocity":0.0,"isReading":true,"idFixation":423},{"gazeX":832.259949,"gazeY":211.259262,"timestamp":170735568.0,"idLine":0,"duration":240.0,"squaredVelocity":0.0,"isReading":true,"idFixation":424},{"gazeX":901.728638,"gazeY":208.181519,"timestamp":170735872.0,"idLine":0,"duration":368.0,"squaredVelocity":0.0,"isReading":true,"idFixation":425},{"gazeX":949.374634,"gazeY":210.655182,"timestamp":170736240.0,"idLine":0,"duration":144.0,"squaredVelocity":0.0,"isReading":true,"idFixation":426},{"gazeX":1036.21887,"gazeY":209.875183,"timestamp":1.707365E+08,"idLine":0,"duration":272.0,"squaredVelocity":0.0,"isReading":true,"idFixation":427},{"gazeX":1148.15894,"gazeY":200.353516,"timestamp":170736912.0,"idLine":0,"duration":160.0,"squaredVelocity":0.0,"isReading":true,"idFixation":428},{"gazeX":1188.04114,"gazeY":201.375671,"timestamp":170737088.0,"idLine":0,"duration":224.0,"squaredVelocity":0.0,"isReading":true,"idFixation":429},{"gazeX":1248.119,"gazeY":208.770142,"timestamp":170737424.0,"idLine":0,"duration":352.0,"squaredVelocity":0.0,"isReading":true,"idFixation":430},{"gazeX":1315.84155,"gazeY":209.695023,"timestamp":1.707378E+08,"idLine":0,"duration":144.0,"squaredVelocity":0.0,"isReading":true,"idFixation":431},{"gazeX":1358.95386,"gazeY":204.24614,"timestamp":170737984.0,"idLine":0,"duration":112.0,"squaredVelocity":0.0,"isReading":true,"idFixation":432},{"gazeX":541.3278,"gazeY":213.079987,"timestamp":1.707382E+08,"idLine":0,"duration":240.0,"squaredVelocity":0.0,"isReading":true,"idFixation":433},{"gazeX":557.3339,"gazeY":229.874588,"timestamp":170738464.0,"idLine":0,"duration":416.0,"squaredVelocity":0.0,"isReading":true,"idFixation":434},{"gazeX":600.809631,"gazeY":228.802887,"timestamp":170738992.0,"idLine":0,"duration":144.0,"squaredVelocity":0.0,"isReading":true,"idFixation":435},{"gazeX":682.6702,"gazeY":219.194138,"timestamp":170739168.0,"idLine":0,"duration":320.0,"squaredVelocity":0.0,"isReading":true,"idFixation":436},{"gazeX":664.0793,"gazeY":215.648941,"timestamp":1.707395E+08,"idLine":0,"duration":144.0,"squaredVelocity":0.0,"isReading":true,"idFixation":437},{"gazeX":725.0048,"gazeY":220.996124,"timestamp":170739664.0,"idLine":0,"duration":208.0,"squaredVelocity":0.0,"isReading":true,"idFixation":438},{"gazeX":773.3963,"gazeY":222.3467,"timestamp":170739888.0,"idLine":0,"duration":112.0,"squaredVelocity":0.0,"isReading":true,"idFixation":439},{"gazeX":784.012451,"gazeY":225.743454,"timestamp":170740016.0,"idLine":0,"duration":320.0,"squaredVelocity":0.0,"isReading":true,"idFixation":440},{"gazeX":835.5352,"gazeY":228.253723,"timestamp":170740336.0,"idLine":0,"duration":192.0,"squaredVelocity":0.0,"isReading":true,"idFixation":441},{"gazeX":883.039368,"gazeY":232.177414,"timestamp":170740592.0,"idLine":0,"duration":320.0,"squaredVelocity":0.0,"isReading":true,"idFixation":442},{"gazeX":940.5045,"gazeY":222.300079,"timestamp":170740944.0,"idLine":0,"duration":112.0,"squaredVelocity":0.0,"isReading":true,"idFixation":443},{"gazeX":965.5063,"gazeY":222.321609,"timestamp":170741056.0,"idLine":0,"duration":192.0,"squaredVelocity":0.0,"isReading":true,"idFixation":444},{"gazeX":1003.5069,"gazeY":226.778122,"timestamp":170741264.0,"idLine":0,"duration":288.0,"squaredVelocity":0.0,"isReading":true,"idFixation":445},{"gazeX":1083.24487,"gazeY":224.109589,"timestamp":170741584.0,"idLine":0,"duration":240.0,"squaredVelocity":0.0,"isReading":true,"idFixation":446},{"gazeX":1150.131,"gazeY":221.397141,"timestamp":170741856.0,"idLine":0,"duration":240.0,"squaredVelocity":0.0,"isReading":true,"idFixation":447},{"gazeX":1230.84888,"gazeY":226.260468,"timestamp":170742112.0,"idLine":0,"duration":224.0,"squaredVelocity":0.0,"isReading":true,"idFixation":448},{"gazeX":1285.54565,"gazeY":221.501434,"timestamp":170742352.0,"idLine":0,"duration":144.0,"squaredVelocity":0.0,"isReading":true,"idFixation":449},{"gazeX":569.821655,"gazeY":244.158539,"timestamp":170742624.0,"idLine":0,"duration":352.0,"squaredVelocity":0.0,"isReading":true,"idFixation":450},{"gazeX":628.553,"gazeY":254.35434,"timestamp":170742992.0,"idLine":0,"duration":128.0,"squaredVelocity":0.0,"isReading":true,"idFixation":451},{"gazeX":635.0987,"gazeY":253.487045,"timestamp":170743136.0,"idLine":0,"duration":320.0,"squaredVelocity":0.0,"isReading":true,"idFixation":452},{"gazeX":572.019348,"gazeY":247.074615,"timestamp":170743456.0,"idLine":0,"duration":176.0,"squaredVelocity":0.0,"isReading":true,"idFixation":453},{"gazeX":626.9836,"gazeY":250.4166,"timestamp":170743648.0,"idLine":0,"duration":320.0,"squaredVelocity":0.0,"isReading":true,"idFixation":454},{"gazeX":684.1435,"gazeY":254.196,"timestamp":170743984.0,"idLine":0,"duration":176.0,"squaredVelocity":0.0,"isReading":true,"idFixation":455},{"gazeX":720.4624,"gazeY":259.694763,"timestamp":170744176.0,"idLine":0,"duration":416.0,"squaredVelocity":0.0,"isReading":true,"idFixation":456},{"gazeX":776.5,"gazeY":256.715942,"timestamp":170744688.0,"idLine":0,"duration":176.0,"squaredVelocity":0.0,"isReading":true,"idFixation":457},{"gazeX":746.901367,"gazeY":255.42923,"timestamp":170744864.0,"idLine":0,"duration":208.0,"squaredVelocity":0.0,"isReading":true,"idFixation":458},{"gazeX":784.336243,"gazeY":261.104218,"timestamp":170745088.0,"idLine":0,"duration":112.0,"squaredVelocity":0.0,"isReading":true,"idFixation":459},{"gazeX":846.7652,"gazeY":254.86055,"timestamp":170745280.0,"idLine":0,"duration":240.0,"squaredVelocity":0.0,"isReading":true,"idFixation":460},{"gazeX":903.7322,"gazeY":254.391388,"timestamp":170745536.0,"idLine":0,"duration":192.0,"squaredVelocity":0.0,"isReading":true,"idFixation":461},{"gazeX":914.2665,"gazeY":252.476669,"timestamp":170745744.0,"idLine":0,"duration":176.0,"squaredVelocity":0.0,"isReading":true,"idFixation":462},{"gazeX":963.667,"gazeY":255.825485,"timestamp":170745936.0,"idLine":0,"duration":256.0,"squaredVelocity":0.0,"isReading":true,"idFixation":463},{"gazeX":1037.29517,"gazeY":250.287643,"timestamp":170746256.0,"idLine":0,"duration":352.0,"squaredVelocity":0.0,"isReading":true,"idFixation":464},{"gazeX":1087.03149,"gazeY":249.323364,"timestamp":170746624.0,"idLine":0,"duration":144.0,"squaredVelocity":0.0,"isReading":true,"idFixation":465},{"gazeX":1097.92078,"gazeY":255.089111,"timestamp":170746784.0,"idLine":0,"duration":192.0,"squaredVelocity":0.0,"isReading":true,"idFixation":466},{"gazeX":1139.41052,"gazeY":262.2219,"timestamp":170746976.0,"idLine":0,"duration":208.0,"squaredVelocity":0.0,"isReading":true,"idFixation":467},{"gazeX":1212.20325,"gazeY":261.82373,"timestamp":1.707473E+08,"idLine":0,"duration":512.0,"squaredVelocity":0.0,"isReading":true,"idFixation":468},{"gazeX":1172.41931,"gazeY":266.284,"timestamp":170747952.0,"idLine":0,"duration":224.0,"squaredVelocity":0.0,"isReading":true,"idFixation":469},{"gazeX":1237.92444,"gazeY":264.957336,"timestamp":1.707482E+08,"idLine":0,"duration":128.0,"squaredVelocity":0.0,"isReading":true,"idFixation":470},{"gazeX":1304.8512,"gazeY":264.997223,"timestamp":170748448.0,"idLine":0,"duration":256.0,"squaredVelocity":0.0,"isReading":true,"idFixation":471},{"gazeX":558.8389,"gazeY":274.050446,"timestamp":1.707489E+08,"idLine":0,"duration":192.0,"squaredVelocity":0.0,"isReading":true,"idFixation":472},{"gazeX":627.7248,"gazeY":280.2759,"timestamp":1.707491E+08,"idLine":0,"duration":256.0,"squaredVelocity":0.0,"isReading":true,"idFixation":473},{"gazeX":651.6989,"gazeY":274.502533,"timestamp":170749360.0,"idLine":0,"duration":256.0,"squaredVelocity":0.0,"isReading":true,"idFixation":474},{"gazeX":748.0593,"gazeY":279.856171,"timestamp":170749712.0,"idLine":0,"duration":160.0,"squaredVelocity":0.0,"isReading":true,"idFixation":475},{"gazeX":806.83374,"gazeY":280.678131,"timestamp":170749984.0,"idLine":0,"duration":416.0,"squaredVelocity":0.0,"isReading":true,"idFixation":476},{"gazeX":851.0066,"gazeY":277.214447,"timestamp":170750448.0,"idLine":0,"duration":256.0,"squaredVelocity":0.0,"isReading":true,"idFixation":477},{"gazeX":802.665161,"gazeY":273.305237,"timestamp":170750720.0,"idLine":0,"duration":208.0,"squaredVelocity":0.0,"isReading":true,"idFixation":478},{"gazeX":830.5869,"gazeY":279.938354,"timestamp":170750928.0,"idLine":0,"duration":320.0,"squaredVelocity":0.0,"isReading":true,"idFixation":479},{"gazeX":931.3549,"gazeY":285.4979,"timestamp":170751280.0,"idLine":0,"duration":144.0,"squaredVelocity":0.0,"isReading":true,"idFixation":480},{"gazeX":886.7955,"gazeY":281.6465,"timestamp":170751552.0,"idLine":0,"duration":176.0,"squaredVelocity":0.0,"isReading":true,"idFixation":481},{"gazeX":1146.9751,"gazeY":573.339966,"timestamp":170793456.0,"idLine":0,"duration":128.0,"squaredVelocity":0.0,"isReading":true,"idFixation":617},{"gazeX":1220.53943,"gazeY":572.423035,"timestamp":1.707936E+08,"idLine":0,"duration":496.0,"squaredVelocity":0.0,"isReading":true,"idFixation":618},{"gazeX":1224.83167,"gazeY":566.627869,"timestamp":170794112.0,"idLine":0,"duration":256.0,"squaredVelocity":0.0,"isReading":false,"idFixation":619},{"gazeX":1277.13232,"gazeY":566.7469,"timestamp":170794384.0,"idLine":0,"duration":192.0,"squaredVelocity":0.0,"isReading":false,"idFixation":620},{"gazeX":1768.26819,"gazeY":385.7897,"timestamp":170794672.0,"idLine":0,"duration":128.0,"squaredVelocity":0.0,"isReading":false,"idFixation":621},{"gazeX":1809.86365,"gazeY":371.76297,"timestamp":170794816.0,"idLine":0,"duration":176.0,"squaredVelocity":0.0,"isReading":false,"idFixation":622},{"gazeX":1731.83752,"gazeY":352.164185,"timestamp":170795024.0,"idLine":0,"duration":128.0,"squaredVelocity":0.0,"isReading":false,"idFixation":623},{"gazeX":1738.20276,"gazeY":353.762054,"timestamp":170795152.0,"idLine":0,"duration":256.0,"squaredVelocity":0.0,"isReading":false,"idFixation":624},{"gazeX":1349.09229,"gazeY":589.704163,"timestamp":170798352.0,"idLine":0,"duration":144.0,"squaredVelocity":0.0,"isReading":false,"idFixation":625},{"gazeX":1305.812,"gazeY":561.314636,"timestamp":170798512.0,"idLine":0,"duration":128.0,"squaredVelocity":0.0,"isReading":false,"idFixation":626},{"gazeX":1721.22949,"gazeY":992.186951,"timestamp":170798752.0,"idLine":0,"duration":128.0,"squaredVelocity":0.0,"isReading":false,"idFixation":627},{"gazeX":1811.85034,"gazeY":956.359253,"timestamp":1.707989E+08,"idLine":0,"duration":208.0,"squaredVelocity":0.0,"isReading":false,"idFixation":628},{"gazeX":1230.94141,"gazeY":473.54248,"timestamp":170801760.0,"idLine":0,"duration":192.0,"squaredVelocity":0.0,"isReading":false,"idFixation":629},{"gazeX":1643.48108,"gazeY":796.9558,"timestamp":1.708021E+08,"idLine":0,"duration":224.0,"squaredVelocity":0.0,"isReading":false,"idFixation":630},{"gazeX":1783.3988,"gazeY":317.804047,"timestamp":170802480.0,"idLine":0,"duration":256.0,"squaredVelocity":0.0,"isReading":false,"idFixation":631},{"gazeX":1739.63928,"gazeY":299.260834,"timestamp":170802752.0,"idLine":0,"duration":144.0,"squaredVelocity":0.0,"isReading":false,"idFixation":632},{"gazeX":1762.63318,"gazeY":369.771759,"timestamp":1.70803E+08,"idLine":0,"duration":400.0,"squaredVelocity":0.0,"isReading":false,"idFixation":633},{"gazeX":1739.914,"gazeY":352.57724,"timestamp":170803680.0,"idLine":0,"duration":400.0,"squaredVelocity":0.0,"isReading":false,"idFixation":634},{"gazeX":1581.729,"gazeY":308.639343,"timestamp":1.708047E+08,"idLine":0,"duration":192.0,"squaredVelocity":0.0,"isReading":false,"idFixation":635},{"gazeX":1530.72791,"gazeY":255.4443,"timestamp":1.708049E+08,"idLine":0,"duration":320.0,"squaredVelocity":0.0,"isReading":false,"idFixation":636},{"gazeX":1521.50476,"gazeY":235.13121,"timestamp":170805232.0,"idLine":0,"duration":224.0,"squaredVelocity":0.0,"isReading":false,"idFixation":637},{"gazeX":1266.357,"gazeY":380.537445,"timestamp":170810976.0,"idLine":0,"duration":240.0,"squaredVelocity":0.0,"isReading":false,"idFixation":638},{"gazeX":1812.64612,"gazeY":314.175781,"timestamp":170811856.0,"idLine":0,"duration":240.0,"squaredVelocity":0.0,"isReading":false,"idFixation":639},{"gazeX":794.804565,"gazeY":92.59382,"timestamp":170812688.0,"idLine":0,"duration":176.0,"squaredVelocity":0.0,"isReading":false,"idFixation":640},{"gazeX":1934.92542,"gazeY":401.5495,"timestamp":170821168.0,"idLine":0,"duration":112.0,"squaredVelocity":0.0,"isReading":false,"idFixation":641},{"gazeX":1892.43115,"gazeY":343.1929,"timestamp":1.708213E+08,"idLine":0,"duration":272.0,"squaredVelocity":0.0,"isReading":false,"idFixation":642},{"gazeX":1313.91553,"gazeY":446.354767,"timestamp":170821680.0,"idLine":0,"duration":416.0,"squaredVelocity":0.0,"isReading":false,"idFixation":643},{"gazeX":1674.64563,"gazeY":947.622,"timestamp":170822192.0,"idLine":0,"duration":128.0,"squaredVelocity":0.0,"isReading":false,"idFixation":644},{"gazeX":478.269165,"gazeY":896.836853,"timestamp":170822416.0,"idLine":0,"duration":176.0,"squaredVelocity":0.0,"isReading":false,"idFixation":645},{"gazeX":2000.24414,"gazeY":312.5689,"timestamp":170822928.0,"idLine":0,"duration":208.0,"squaredVelocity":0.0,"isReading":false,"idFixation":646},{"gazeX":1941.06677,"gazeY":315.7039,"timestamp":170823216.0,"idLine":0,"duration":512.0,"squaredVelocity":0.0,"isReading":false,"idFixation":647},{"gazeX":1271.28906,"gazeY":414.986328,"timestamp":170824432.0,"idLine":0,"duration":208.0,"squaredVelocity":0.0,"isReading":false,"idFixation":648},{"gazeX":1881.17456,"gazeY":247.446,"timestamp":170824736.0,"idLine":0,"duration":208.0,"squaredVelocity":0.0,"isReading":false,"idFixation":649},{"gazeX":1047.55847,"gazeY":276.728149,"timestamp":170825040.0,"idLine":0,"duration":304.0,"squaredVelocity":0.0,"isReading":false,"idFixation":650},{"gazeX":756.1213,"gazeY":202.208069,"timestamp":170825472.0,"idLine":0,"duration":176.0,"squaredVelocity":0.0,"isReading":false,"idFixation":651},{"gazeX":705.367432,"gazeY":162.731613,"timestamp":170825664.0,"idLine":0,"duration":112.0,"squaredVelocity":0.0,"isReading":false,"idFixation":652},{"gazeX":138.730042,"gazeY":72.4496155,"timestamp":170826064.0,"idLine":0,"duration":384.0,"squaredVelocity":0.0,"isReading":false,"idFixation":653},{"gazeX":133.183563,"gazeY":37.9135132,"timestamp":170826512.0,"idLine":0,"duration":128.0,"squaredVelocity":0.0,"isReading":false,"idFixation":654},{"gazeX":132.796188,"gazeY":88.43512,"timestamp":170826656.0,"idLine":0,"duration":304.0,"squaredVelocity":0.0,"isReading":false,"idFixation":655},{"gazeX":823.8957,"gazeY":534.115967,"timestamp":170827424.0,"idLine":0,"duration":112.0,"squaredVelocity":0.0,"isReading":false,"idFixation":656},{"gazeX":934.075,"gazeY":594.7733,"timestamp":170827712.0,"idLine":0,"duration":288.0,"squaredVelocity":0.0,"isReading":false,"idFixation":657},{"gazeX":1514.917,"gazeY":952.5275,"timestamp":1.708281E+08,"idLine":0,"duration":208.0,"squaredVelocity":0.0,"isReading":false,"idFixation":658},{"gazeX":1789.67,"gazeY":311.393768,"timestamp":170828432.0,"idLine":0,"duration":160.0,"squaredVelocity":0.0,"isReading":false,"idFixation":659},{"gazeX":1766.68677,"gazeY":309.8296,"timestamp":170828592.0,"idLine":0,"duration":432.0,"squaredVelocity":0.0,"isReading":false,"idFixation":660},{"gazeX":1746.90771,"gazeY":280.024872,"timestamp":1.70829E+08,"idLine":0,"duration":112.0,"squaredVelocity":0.0,"isReading":false,"idFixation":661},{"gazeX":1757.864,"gazeY":257.248718,"timestamp":170829120.0,"idLine":0,"duration":256.0,"squaredVelocity":0.0,"isReading":false,"idFixation":662},{"gazeX":1817.23669,"gazeY":219.519516,"timestamp":170829392.0,"idLine":0,"duration":240.0,"squaredVelocity":0.0,"isReading":false,"idFixation":663},{"gazeX":1810.40686,"gazeY":226.755981,"timestamp":170829632.0,"idLine":0,"duration":144.0,"squaredVelocity":0.0,"isReading":false,"idFixation":664},{"gazeX":2129.34082,"gazeY":97.24604,"timestamp":170839584.0,"idLine":0,"duration":160.0,"squaredVelocity":0.0,"isReading":false,"idFixation":665}]